MANIFEST.in
README.md
setup.cfg
setup.py
Halocoin.egg-info/PKG-INFO
Halocoin.egg-info/SOURCES.txt
Halocoin.egg-info/dependency_links.txt
Halocoin.egg-info/entry_points.txt
Halocoin.egg-info/requires.txt
Halocoin.egg-info/top_level.txt
halocoin/__init__.py
halocoin/account.py
halocoin/api.py
halocoin/blockchain.py
halocoin/cli.py
halocoin/custom.py
halocoin/database.py
halocoin/engine.py
halocoin/miner.py
halocoin/peer_check.py
halocoin/peer_listen.py
halocoin/service.py
halocoin/tools.py
halocoin/model/__init__.py
halocoin/model/wallet.py
halocoin/ntwrk/__init__.py
halocoin/ntwrk/message.py
halocoin/ntwrk/response.py
halocoin/static/favicon.ico
halocoin/static/manifest.json
halocoin/static/dashboard/css/bootstrap.min.css
halocoin/static/dashboard/css/material-dashboard.css
halocoin/static/dashboard/img/apple-icon.png
halocoin/static/dashboard/img/cover.jpeg
halocoin/static/dashboard/img/favicon.png
halocoin/static/dashboard/img/mask.png
halocoin/static/dashboard/img/new_logo.png
halocoin/static/dashboard/img/sidebar-1.jpg
halocoin/static/dashboard/img/sidebar-2.jpg
halocoin/static/dashboard/img/sidebar-3.jpg
halocoin/static/dashboard/img/sidebar-4.jpg
halocoin/static/dashboard/img/tim_80x80.png
halocoin/static/dashboard/img/faces/marc.jpg
halocoin/static/dashboard/js/arrive.min.js
halocoin/static/dashboard/js/bootstrap.min.js
halocoin/static/dashboard/js/chartist.min.js
halocoin/static/dashboard/js/demo.js
halocoin/static/dashboard/js/jquery-3.2.1.min.js
halocoin/static/dashboard/js/material-dashboard.js
halocoin/static/dashboard/js/material.min.js
halocoin/static/dashboard/js/perfect-scrollbar.jquery.min.js
halocoin/static/dashboard/sass/material-dashboard.scss
halocoin/static/dashboard/sass/md/_alerts.scss
halocoin/static/dashboard/sass/md/_buttons.scss
halocoin/static/dashboard/sass/md/_cards.scss
halocoin/static/dashboard/sass/md/_chartist.scss
halocoin/static/dashboard/sass/md/_checkboxes.scss
halocoin/static/dashboard/sass/md/_colors.scss
halocoin/static/dashboard/sass/md/_dialogs.scss
halocoin/static/dashboard/sass/md/_dropdown.scss
halocoin/static/dashboard/sass/md/_footers.scss
halocoin/static/dashboard/sass/md/_forms.scss
