Metadata-Version: 1.0
Name: Halocoin
Version: 0.1.0.4
Summary: An educational blockchain implementation. Forked from zack-bitcoin/basiccoin
Home-page: https://github.com/halilozercan/halocoin
Author: Halil Ozercan
Author-email: halilozercan@gmail.com
License: UNKNOWN
Platform: UNKNOWN
